RhinoAccum/__init__.py
RhinoAccum/npsum.py
RhinoAccum1-1.1.dist-info/LICENSE
RhinoAccum1-1.1.dist-info/METADATA
RhinoAccum1-1.1.dist-info/WHEEL
RhinoAccum1-1.1.dist-info/top_level.txt
RhinoAccum1-1.1.dist-info/RECORD
