Metadata-Version: 2.1
Name: RhinoAccum1
Version: 1.1
Summary: too simple
Author: Rhinozh
Author-email: Rhinozh@163.com
License: UNKNOWN
Platform: UNKNOWN
Classifier: Programming Language :: Python :: 3
Classifier: License :: OSI Approved :: MIT License
Classifier: Operating System :: OS Independent
Requires-Python: >=3
License-File: LICENSE
Requires-Dist: numpy
